{
  "nombre_colegio": "LICEO BICENTENARIO POLITECNICO HEROES DE LA CONCEPCIÓN",
  "rbd": "4483",
  "dependencia": "Municipalizado",
  "comuna": "Laja",
  "GSE": "",
  "indicadores": {
    "indicador-1-2": {
      "coordsX": [
        "2022"
      ],
      "dataPoints": [
        {
          "backgroundColor": "#5c5c5c",
          "borderColor": "#5c5c5c",
          "data": [
            ""
          ],
          "label": "Puntaje promedio nacional del mismo GSE"
        },
        {
          "backgroundColor": "#043aa2",
          "borderColor": "#043aa2",
          "data": [
            ""
          ],
          "label": "Puntaje promedio del establecimiento"
        }
      ],
      "dif": null,
      "format": 4,
      "mDif": "",
      "sigDif": null
    },
    "indicador-10": {
      "coordsX": [
        [
          "Números",
          "y Operaciones"
        ],
        [
          "Patrones y Álgebra"
        ],
        [
          "Geometría",
          "Medición"
        ],
        [
          "Datos y Probabilidades"
        ]
      ],
      "dataPoints": [
        [],
        [],
        [],
        [],
        []
      ],
      "dif": null,
      "format": 1,
      "mDif": [
        "",
        "",
        "",
        "",
        ""
      ],
      "sigDif": null
    },
    "indicador-11": {
      "coordsX": [
        "2016",
        "2017",
        "2018",
        "2022",
        "2023"
      ],
      "dataPoints": [
        "75",
        "75",
        "74",
        "74",
        "74"
      ],
      "dif": [
        {
          "dif": "0",
          "difKey": "2017_2016"
        },
        {
          "dif": "-1",
          "difKey": "2018_2017"
        },
        {
          "dif": "0",
          "difKey": "2022_2018"
        },
        {
          "dif": "0",
          "difKey": "2023_2022"
        }
      ],
      "format": 1,
      "mDif": null,
      "sigDif": [
        {
          "sigDif": "0",
          "sigDifKey": "2017_2016"
        },
        {
          "sigDif": "0",
          "sigDifKey": "2018_2017"
        },
        {
          "sigDif": "0",
          "sigDifKey": "2022_2018"
        },
        {
          "sigDif": "0",
          "sigDifKey": "2023_2022"
        }
      ]
    },
    "indicador-11-2": {
      "coordsX": [
        "2022"
      ],
      "dataPoints": [
        {
          "backgroundColor": "#5c5c5c",
          "borderColor": "#5c5c5c",
          "data": [
            "74"
          ],
          "label": "Puntaje promedio nacional del mismo GSE"
        },
        {
          "backgroundColor": "#043aa2",
          "borderColor": "#043aa2",
          "data": [
            "74"
          ],
          "label": "Puntaje promedio del establecimiento"
        }
      ],
      "dif": null,
      "format": 4,
      "mDif": "",
      "sigDif": null
    },
    "indicador-12": {
      "coordsX": [
        "2016",
        "2017",
        "2018",
        "2022",
        "2023"
      ],
      "dataPoints": [
        "71",
        "74",
        "74",
        "75",
        "76"
      ],
      "dif": [
        {
          "dif": "3",
          "difKey": "2017_2016"
        },
        {
          "dif": "0",
          "difKey": "2018_2017"
        },
        {
          "dif": "1",
          "difKey": "2022_2018"
        },
        {
          "dif": "1",
          "difKey": "2023_2022"
        }
      ],
      "format": 1,
      "mDif": null,
      "sigDif": [
        {
          "sigDif": "0",
          "sigDifKey": "2017_2016"
        },
        {
          "sigDif": "0",
          "sigDifKey": "2018_2017"
        },
        {
          "sigDif": "0",
          "sigDifKey": "2022_2018"
        },
        {
          "sigDif": "0",
          "sigDifKey": "2023_2022"
        }
      ]
    },
    "indicador-12-2": {
      "coordsX": [
        "2022"
      ],
      "dataPoints": [
        {
          "backgroundColor": "#5c5c5c",
          "borderColor": "#5c5c5c",
          "data": [
            "75"
          ],
          "label": "Puntaje promedio nacional del mismo GSE"
        },
        {
          "backgroundColor": "#043aa2",
          "borderColor": "#043aa2",
          "data": [
            "76"
          ],
          "label": "Puntaje promedio del establecimiento"
        }
      ],
      "dif": null,
      "format": 4,
      "mDif": "",
      "sigDif": null
    },
    "indicador-13": {
      "coordsX": [
        "2016",
        "2017",
        "2018",
        "2022",
        "2023"
      ],
      "dataPoints": [
        "77",
        "78",
        "77",
        "78",
        "78"
      ],
      "dif": [
        {
          "dif": "1",
          "difKey": "2017_2016"
        },
        {
          "dif": "-1",
          "difKey": "2018_2017"
        },
        {
          "dif": "1",
          "difKey": "2022_2018"
        },
        {
          "dif": "0",
          "difKey": "2023_2022"
        }
      ],
      "format": 1,
      "mDif": null,
      "sigDif": [
        {
          "sigDif": "0",
          "sigDifKey": "2017_2016"
        },
        {
          "sigDif": "0",
          "sigDifKey": "2018_2017"
        },
        {
          "sigDif": "0",
          "sigDifKey": "2022_2018"
        },
        {
          "sigDif": "0",
          "sigDifKey": "2023_2022"
        }
      ]
    },
    "indicador-13-2": {
      "coordsX": [
        "2022"
      ],
      "dataPoints": [
        {
          "backgroundColor": "#5c5c5c",
          "borderColor": "#5c5c5c",
          "data": [
            "77"
          ],
          "label": "Puntaje promedio nacional del mismo GSE"
        },
        {
          "backgroundColor": "#043aa2",
          "borderColor": "#043aa2",
          "data": [
            "78"
          ],
          "label": "Puntaje promedio del establecimiento"
        }
      ],
      "dif": null,
      "format": 4,
      "mDif": "",
      "sigDif": null
    },
    "indicador-14": {
      "coordsX": [
        "2016",
        "2017",
        "2018",
        "2022",
        "2023"
      ],
      "dataPoints": [
        "68",
        "72",
        "69",
        "70",
        "73"
      ],
      "dif": [
        {
          "dif": "4",
          "difKey": "2017_2016"
        },
        {
          "dif": "-3",
          "difKey": "2018_2017"
        },
        {
          "dif": "1",
          "difKey": "2022_2018"
        },
        {
          "dif": "3",
          "difKey": "2023_2022"
        }
      ],
      "format": 1,
      "mDif": null,
      "sigDif": [
        {
          "sigDif": "1",
          "sigDifKey": "2017_2016"
        },
        {
          "sigDif": "0",
          "sigDifKey": "2018_2017"
        },
        {
          "sigDif": "0",
          "sigDifKey": "2022_2018"
        },
        {
          "sigDif": "0",
          "sigDifKey": "2023_2022"
        }
      ]
    },
    "indicador-14-2": {
      "coordsX": [
        "2022"
      ],
      "dataPoints": [
        {
          "backgroundColor": "#5c5c5c",
          "borderColor": "#5c5c5c",
          "data": [
            "71"
          ],
          "label": "Puntaje promedio nacional del mismo GSE"
        },
        {
          "backgroundColor": "#043aa2",
          "borderColor": "#043aa2",
          "data": [
            "73"
          ],
          "label": "Puntaje promedio del establecimiento"
        }
      ],
      "dif": null,
      "format": 4,
      "mDif": "",
      "sigDif": null
    },
    "indicador-15": {
      "coordsX": [
        "2016",
        "2017",
        "2018",
        "2022",
        "2023"
      ],
      "dataPoints": [
        "240",
        "251",
        "242",
        "246",
        "245"
      ],
      "dif": [
        {
          "dif": "11",
          "difKey": "2017_2016"
        },
        {
          "dif": "-9",
          "difKey": "2018_2017"
        },
        {
          "dif": "4",
          "difKey": "2022_2018"
        },
        {
          "dif": "-1",
          "difKey": "2023_2022"
        }
      ],
      "format": 1,
      "mDif": null,
      "sigDif": [
        {
          "sigDif": "1",
          "sigDifKey": "2017_2016"
        },
        {
          "sigDif": "-1",
          "sigDifKey": "2018_2017"
        },
        {
          "sigDif": "0",
          "sigDifKey": "2022_2018"
        },
        {
          "sigDif": "0",
          "sigDifKey": "2023_2022"
        }
      ]
    },
    "indicador-15-2": {
      "coordsX": [
        "2022"
      ],
      "dataPoints": [
        {
          "backgroundColor": "#5c5c5c",
          "borderColor": "#5c5c5c",
          "data": [
            "240"
          ],
          "label": "Puntaje promedio nacional del mismo GSE"
        },
        {
          "backgroundColor": "#043aa2",
          "borderColor": "#043aa2",
          "data": [
            "245"
          ],
          "label": "Puntaje promedio del establecimiento"
        }
      ],
      "dif": null,
      "format": 4,
      "mDif": "",
      "sigDif": null
    },
    "indicador-16": {
      "coordsX": [
        "2016",
        "2017",
        "2018",
        "2022",
        "2023"
      ],
      "dataPoints": [
        {
          "backgroundColor": "#87b4e2",
          "data": [
            "55.0",
            "51.6",
            "53.9",
            "51.7",
            "53.3"
          ],
          "label": "Nivel insuficiente"
        },
        {
          "backgroundColor": "#3dacea",
          "data": [
            "29.4",
            "26.2",
            "35.1",
            "30.2",
            "29.4"
          ],
          "label": "Nivel elemental"
        },
        {
          "backgroundColor": "#043aa2",
          "data": [
            "15.5",
            "22.2",
            "11.0",
            "18.0",
            "17.3"
          ],
          "label": "Nivel adecuado"
        }
      ],
      "dif": null,
      "format": 2,
      "mDif": [
        {
          "value": "",
          "year": "2016"
        },
        {
          "value": "",
          "year": "2017"
        },
        {
          "value": "",
          "year": "2018"
        },
        {
          "value": "",
          "year": "2022"
        },
        {
          "value": "",
          "year": "2023"
        },
        {
          "value": "",
          "year": "2016"
        },
        {
          "value": "",
          "year": "2017"
        },
        {
          "value": "",
          "year": "2018"
        },
        {
          "value": "",
          "year": "2022"
        },
        {
          "value": "",
          "year": "2023"
        },
        {
          "value": "",
          "year": "2016"
        },
        {
          "value": "",
          "year": "2017"
        },
        {
          "value": "",
          "year": "2018"
        },
        {
          "value": "",
          "year": "2022"
        },
        {
          "value": "",
          "year": "2023"
        }
      ],
      "sigDif": null
    },
    "indicador-17": {
      "coordsX": [
        "Localizar",
        "Interpetrar y relacionar",
        "Reflexionar"
      ],
      "dataPoints": [
        [
          5
        ],
        [
          5
        ],
        [
          5
        ]
      ],
      "dif": null,
      "format": 1,
      "mDif": [
        "",
        "",
        ""
      ],
      "sigDif": null
    },
    "indicador-18": {
      "coordsX": [
        "2016",
        "2017",
        "2018",
        "2022",
        "2023"
      ],
      "dataPoints": [
        "265",
        "260",
        "261",
        "257",
        "255"
      ],
      "dif": [
        {
          "dif": "-5",
          "difKey": "2017_2016"
        },
        {
          "dif": "1",
          "difKey": "2018_2017"
        },
        {
          "dif": "-4",
          "difKey": "2022_2018"
        },
        {
          "dif": "-2",
          "difKey": "2023_2022"
        }
      ],
      "format": 1,
      "mDif": null,
      "sigDif": [
        {
          "sigDif": "0",
          "sigDifKey": "2017_2016"
        },
        {
          "sigDif": "0",
          "sigDifKey": "2018_2017"
        },
        {
          "sigDif": "0",
          "sigDifKey": "2022_2018"
        },
        {
          "sigDif": "0",
          "sigDifKey": "2023_2022"
        }
      ]
    },
    "indicador-18-2": {
      "coordsX": [
        "2022"
      ],
      "dataPoints": [
        {
          "backgroundColor": "#5c5c5c",
          "borderColor": "#5c5c5c",
          "data": [
            "244"
          ],
          "label": "Puntaje promedio nacional del mismo GSE"
        },
        {
          "backgroundColor": "#043aa2",
          "borderColor": "#043aa2",
          "data": [
            "255"
          ],
          "label": "Puntaje promedio del establecimiento"
        }
      ],
      "dif": null,
      "format": 4,
      "mDif": "",
      "sigDif": null
    },
    "indicador-19": {
      "coordsX": [
        "2016",
        "2017",
        "2018",
        "2022",
        "2023"
      ],
      "dataPoints": [
        {
          "backgroundColor": "#87b4e2",
          "data": [
            "43.9",
            "44.0",
            "47.0",
            "46.1",
            "50.0"
          ],
          "label": "Nivel insuficiente"
        },
        {
          "backgroundColor": "#3dacea",
          "data": [
            "37.9",
            "40.1",
            "37.4",
            "42.2",
            "35.0"
          ],
          "label": "Nivel elemental"
        },
        {
          "backgroundColor": "#043aa2",
          "data": [
            "18.2",
            "16.0",
            "15.5",
            "11.7",
            "15.0"
          ],
          "label": "Nivel adecuado"
        }
      ],
      "dif": null,
      "format": 2,
      "mDif": [
        {
          "value": "",
          "year": "2016"
        },
        {
          "value": "",
          "year": "2017"
        },
        {
          "value": "",
          "year": "2018"
        },
        {
          "value": "",
          "year": "2022"
        },
        {
          "value": "",
          "year": "2023"
        },
        {
          "value": "",
          "year": "2016"
        },
        {
          "value": "",
          "year": "2017"
        },
        {
          "value": "",
          "year": "2018"
        },
        {
          "value": "",
          "year": "2022"
        },
        {
          "value": "",
          "year": "2023"
        },
        {
          "value": "",
          "year": "2016"
        },
        {
          "value": "",
          "year": "2017"
        },
        {
          "value": "",
          "year": "2018"
        },
        {
          "value": "",
          "year": "2022"
        },
        {
          "value": "",
          "year": "2023"
        }
      ],
      "sigDif": null
    },
    "indicador-2-2": {
      "coordsX": [
        "2022"
      ],
      "dataPoints": [
        {
          "backgroundColor": "#5c5c5c",
          "borderColor": "#5c5c5c",
          "data": [
            ""
          ],
          "label": "Puntaje promedio nacional del mismo GSE"
        },
        {
          "backgroundColor": "#043aa2",
          "borderColor": "#043aa2",
          "data": [
            ""
          ],
          "label": "Puntaje promedio del establecimiento"
        }
      ],
      "dif": null,
      "format": 4,
      "mDif": "",
      "sigDif": null
    },
    "indicador-20": {
      "coordsX": [
        [
          "Números"
        ],
        [
          "Álgebra y",
          "funciones"
        ],
        [
          "Geometría"
        ],
        [
          "Probabilidad y",
          "estadística"
        ]
      ],
      "dataPoints": [
        [
          5
        ],
        [
          5
        ],
        [
          5
        ],
        [
          5
        ]
      ],
      "dif": null,
      "format": 1,
      "mDif": [
        "",
        "",
        "",
        ""
      ],
      "sigDif": null
    },
    "indicador-3-2": {
      "coordsX": [
        "2022"
      ],
      "dataPoints": [
        {
          "backgroundColor": "#5c5c5c",
          "borderColor": "#5c5c5c",
          "data": [
            ""
          ],
          "label": "Puntaje promedio nacional del mismo GSE"
        },
        {
          "backgroundColor": "#043aa2",
          "borderColor": "#043aa2",
          "data": [
            ""
          ],
          "label": "Puntaje promedio del establecimiento"
        }
      ],
      "dif": null,
      "format": 4,
      "mDif": "",
      "sigDif": null
    },
    "indicador-4-2": {
      "coordsX": [
        "2022"
      ],
      "dataPoints": [
        {
          "backgroundColor": "#5c5c5c",
          "borderColor": "#5c5c5c",
          "data": [
            ""
          ],
          "label": "Puntaje promedio nacional del mismo GSE"
        },
        {
          "backgroundColor": "#043aa2",
          "borderColor": "#043aa2",
          "data": [
            ""
          ],
          "label": "Puntaje promedio del establecimiento"
        }
      ],
      "dif": null,
      "format": 4,
      "mDif": "",
      "sigDif": null
    },
    "indicador-5-2": {
      "coordsX": [
        "2022"
      ],
      "dataPoints": [
        {
          "backgroundColor": "#5c5c5c",
          "borderColor": "#5c5c5c",
          "data": [
            ""
          ],
          "label": "Puntaje promedio nacional del mismo GSE"
        },
        {
          "backgroundColor": "#043aa2",
          "borderColor": "#043aa2",
          "data": [
            ""
          ],
          "label": "Puntaje promedio del establecimiento"
        }
      ],
      "dif": null,
      "format": 4,
      "mDif": "",
      "sigDif": null
    },
    "indicador-7": {
      "coordsX": [
        "Localizar",
        "Interpretar y relacionar",
        "Reflexionar"
      ],
      "dataPoints": [
        [],
        [],
        []
      ],
      "dif": null,
      "format": 1,
      "mDif": [
        "",
        "",
        ""
      ],
      "sigDif": null
    },
    "indicador-8-2": {
      "coordsX": [
        "2022"
      ],
      "dataPoints": [
        {
          "backgroundColor": "#5c5c5c",
          "borderColor": "#5c5c5c",
          "data": [
            ""
          ],
          "label": "Puntaje promedio nacional del mismo GSE"
        },
        {
          "backgroundColor": "#043aa2",
          "borderColor": "#043aa2",
          "data": [
            ""
          ],
          "label": "Puntaje promedio del establecimiento"
        }
      ],
      "dif": null,
      "format": 4,
      "mDif": "",
      "sigDif": null
    }
  },
  "dimensiones": {
    "dimension-38": {
      "coordsX": [
        "2016",
        "2017",
        "2018",
        "2022",
        "2023"
      ],
      "dataPoints": [
        "73",
        "73",
        "71",
        "72",
        "71"
      ],
      "dif": [
        {
          "dif": "0",
          "difKey": "2017_2016"
        },
        {
          "dif": "-2",
          "difKey": "2018_2017"
        },
        {
          "dif": "1",
          "difKey": "2022_2018"
        },
        {
          "dif": "-1",
          "difKey": "2023_2022"
        }
      ],
      "format": 1,
      "mDif": null,
      "sigDif": [
        {
          "sigDif": "0",
          "sigDifKey": "2017_2016"
        },
        {
          "sigDif": "0",
          "sigDifKey": "2018_2017"
        },
        {
          "sigDif": "0",
          "sigDifKey": "2022_2018"
        },
        {
          "sigDif": "0",
          "sigDifKey": "2023_2022"
        }
      ]
    },
    "dimension-39": {
      "coordsX": [
        "2016",
        "2017",
        "2018",
        "2022",
        "2023"
      ],
      "dataPoints": [
        "76",
        "77",
        "77",
        "76",
        "76"
      ],
      "dif": [
        {
          "dif": "1",
          "difKey": "2017_2016"
        },
        {
          "dif": "0",
          "difKey": "2018_2017"
        },
        {
          "dif": "-1",
          "difKey": "2022_2018"
        },
        {
          "dif": "0",
          "difKey": "2023_2022"
        }
      ],
      "format": 1,
      "mDif": null,
      "sigDif": [
        {
          "sigDif": "0",
          "sigDifKey": "2017_2016"
        },
        {
          "sigDif": "0",
          "sigDifKey": "2018_2017"
        },
        {
          "sigDif": "0",
          "sigDifKey": "2022_2018"
        },
        {
          "sigDif": "0",
          "sigDifKey": "2023_2022"
        }
      ]
    },
    "dimension-40": {
      "coordsX": [
        "2016",
        "2017",
        "2018",
        "2022",
        "2023"
      ],
      "dataPoints": [
        "66",
        "70",
        "69",
        "69",
        "70"
      ],
      "dif": [
        {
          "dif": "4",
          "difKey": "2017_2016"
        },
        {
          "dif": "-1",
          "difKey": "2018_2017"
        },
        {
          "dif": "0",
          "difKey": "2022_2018"
        },
        {
          "dif": "1",
          "difKey": "2023_2022"
        }
      ],
      "format": 1,
      "mDif": null,
      "sigDif": [
        {
          "sigDif": "1",
          "sigDifKey": "2017_2016"
        },
        {
          "sigDif": "0",
          "sigDifKey": "2018_2017"
        },
        {
          "sigDif": "0",
          "sigDifKey": "2022_2018"
        },
        {
          "sigDif": "0",
          "sigDifKey": "2023_2022"
        }
      ]
    },
    "dimension-41": {
      "coordsX": [
        "2016",
        "2017",
        "2018",
        "2022",
        "2023"
      ],
      "dataPoints": [
        "78",
        "80",
        "78",
        "79",
        "83"
      ],
      "dif": [
        {
          "dif": "2",
          "difKey": "2017_2016"
        },
        {
          "dif": "-2",
          "difKey": "2018_2017"
        },
        {
          "dif": "1",
          "difKey": "2022_2018"
        },
        {
          "dif": "4",
          "difKey": "2023_2022"
        }
      ],
      "format": 1,
      "mDif": null,
      "sigDif": [
        {
          "sigDif": "0",
          "sigDifKey": "2017_2016"
        },
        {
          "sigDif": "0",
          "sigDifKey": "2018_2017"
        },
        {
          "sigDif": "0",
          "sigDifKey": "2022_2018"
        },
        {
          "sigDif": "1",
          "sigDifKey": "2023_2022"
        }
      ]
    },
    "dimension-42": {
      "coordsX": [
        "2016",
        "2017",
        "2018",
        "2022",
        "2023"
      ],
      "dataPoints": [
        "70",
        "74",
        "74",
        "76",
        "76"
      ],
      "dif": [
        {
          "dif": "4",
          "difKey": "2017_2016"
        },
        {
          "dif": "0",
          "difKey": "2018_2017"
        },
        {
          "dif": "2",
          "difKey": "2022_2018"
        },
        {
          "dif": "0",
          "difKey": "2023_2022"
        }
      ],
      "format": 1,
      "mDif": null,
      "sigDif": [
        {
          "sigDif": "1",
          "sigDifKey": "2017_2016"
        },
        {
          "sigDif": "0",
          "sigDifKey": "2018_2017"
        },
        {
          "sigDif": "0",
          "sigDifKey": "2022_2018"
        },
        {
          "sigDif": "0",
          "sigDifKey": "2023_2022"
        }
      ]
    },
    "dimension-43": {
      "coordsX": [
        "2016",
        "2017",
        "2018",
        "2022",
        "2023"
      ],
      "dataPoints": [
        "77",
        "77",
        "78",
        "80",
        "80"
      ],
      "dif": [
        {
          "dif": "0",
          "difKey": "2017_2016"
        },
        {
          "dif": "1",
          "difKey": "2018_2017"
        },
        {
          "dif": "2",
          "difKey": "2022_2018"
        },
        {
          "dif": "0",
          "difKey": "2023_2022"
        }
      ],
      "format": 1,
      "mDif": null,
      "sigDif": [
        {
          "sigDif": "0",
          "sigDifKey": "2017_2016"
        },
        {
          "sigDif": "0",
          "sigDifKey": "2018_2017"
        },
        {
          "sigDif": "0",
          "sigDifKey": "2022_2018"
        },
        {
          "sigDif": "0",
          "sigDifKey": "2023_2022"
        }
      ]
    },
    "dimension-44": {
      "coordsX": [
        "2016",
        "2017",
        "2018",
        "2022",
        "2023"
      ],
      "dataPoints": [
        "74",
        "76",
        "75",
        "75",
        "74"
      ],
      "dif": [
        {
          "dif": "2",
          "difKey": "2017_2016"
        },
        {
          "dif": "-1",
          "difKey": "2018_2017"
        },
        {
          "dif": "0",
          "difKey": "2022_2018"
        },
        {
          "dif": "-1",
          "difKey": "2023_2022"
        }
      ],
      "format": 1,
      "mDif": null,
      "sigDif": [
        {
          "sigDif": "0",
          "sigDifKey": "2017_2016"
        },
        {
          "sigDif": "0",
          "sigDifKey": "2018_2017"
        },
        {
          "sigDif": "0",
          "sigDifKey": "2022_2018"
        },
        {
          "sigDif": "0",
          "sigDifKey": "2023_2022"
        }
      ]
    },
    "dimension-45": {
      "coordsX": [
        "2016",
        "2017",
        "2018",
        "2022",
        "2023"
      ],
      "dataPoints": [
        "78",
        "81",
        "79",
        "80",
        "80"
      ],
      "dif": [
        {
          "dif": "3",
          "difKey": "2017_2016"
        },
        {
          "dif": "-2",
          "difKey": "2018_2017"
        },
        {
          "dif": "1",
          "difKey": "2022_2018"
        },
        {
          "dif": "0",
          "difKey": "2023_2022"
        }
      ],
      "format": 1,
      "mDif": null,
      "sigDif": [
        {
          "sigDif": "0",
          "sigDifKey": "2017_2016"
        },
        {
          "sigDif": "0",
          "sigDifKey": "2018_2017"
        },
        {
          "sigDif": "0",
          "sigDifKey": "2022_2018"
        },
        {
          "sigDif": "0",
          "sigDifKey": "2023_2022"
        }
      ]
    },
    "dimension-46": {
      "coordsX": [
        "2016",
        "2017",
        "2018",
        "2022",
        "2023"
      ],
      "dataPoints": [
        "63",
        "67",
        "67",
        "69",
        "73"
      ],
      "dif": [
        {
          "dif": "4",
          "difKey": "2017_2016"
        },
        {
          "dif": "0",
          "difKey": "2018_2017"
        },
        {
          "dif": "2",
          "difKey": "2022_2018"
        },
        {
          "dif": "4",
          "difKey": "2023_2022"
        }
      ],
      "format": 1,
      "mDif": null,
      "sigDif": [
        {
          "sigDif": "0",
          "sigDifKey": "2017_2016"
        },
        {
          "sigDif": "0",
          "sigDifKey": "2018_2017"
        },
        {
          "sigDif": "0",
          "sigDifKey": "2022_2018"
        },
        {
          "sigDif": "0",
          "sigDifKey": "2023_2022"
        }
      ]
    },
    "dimension-47": {
      "coordsX": [
        "2016",
        "2017",
        "2018",
        "2022",
        "2023"
      ],
      "dataPoints": [
        "74",
        "80",
        "74",
        "75",
        "79"
      ],
      "dif": [
        {
          "dif": "6",
          "difKey": "2017_2016"
        },
        {
          "dif": "-6",
          "difKey": "2018_2017"
        },
        {
          "dif": "1",
          "difKey": "2022_2018"
        },
        {
          "dif": "4",
          "difKey": "2023_2022"
        }
      ],
      "format": 1,
      "mDif": null,
      "sigDif": [
        {
          "sigDif": "1",
          "sigDifKey": "2017_2016"
        },
        {
          "sigDif": "-1",
          "sigDifKey": "2018_2017"
        },
        {
          "sigDif": "0",
          "sigDifKey": "2022_2018"
        },
        {
          "sigDif": "0",
          "sigDifKey": "2023_2022"
        }
      ]
    },
    "dimension-48": {
      "coordsX": [
        "2016",
        "2017",
        "2018",
        "2022",
        "2023"
      ],
      "dataPoints": [
        "65",
        "68",
        "66",
        "64",
        "66"
      ],
      "dif": [
        {
          "dif": "3",
          "difKey": "2017_2016"
        },
        {
          "dif": "-2",
          "difKey": "2018_2017"
        },
        {
          "dif": "-2",
          "difKey": "2022_2018"
        },
        {
          "dif": "2",
          "difKey": "2023_2022"
        }
      ],
      "format": 1,
      "mDif": null,
      "sigDif": [
        {
          "sigDif": "0",
          "sigDifKey": "2017_2016"
        },
        {
          "sigDif": "0",
          "sigDifKey": "2018_2017"
        },
        {
          "sigDif": "0",
          "sigDifKey": "2022_2018"
        },
        {
          "sigDif": "0",
          "sigDifKey": "2023_2022"
        }
      ]
    }
  }
}