{
  "nombre_colegio": "ESCUELA BERNARDO PHILIPPI",
  "rbd": "7976",
  "dependencia": "Municipalizado",
  "comuna": "Frutillar",
  "GSE": "Medio",
  "indicadores": {
    "indicador-1": {
      "coordsX": [
        "2016",
        "2017",
        "2018",
        "2022",
        "2023"
      ],
      "dataPoints": [
        "73",
        "69",
        "72",
        "74",
        "71"
      ],
      "dif": [
        {
          "dif": "-4",
          "difKey": "2017_2016"
        },
        {
          "dif": "3",
          "difKey": "2018_2017"
        },
        {
          "dif": "2",
          "difKey": "2022_2018"
        },
        {
          "dif": "-3",
          "difKey": "2023_2022"
        }
      ],
      "format": 1,
      "mDif": null,
      "sigDif": [
        {
          "sigDif": "-1",
          "sigDifKey": "2017_2016"
        },
        {
          "sigDif": "0",
          "sigDifKey": "2018_2017"
        },
        {
          "sigDif": "0",
          "sigDifKey": "2022_2018"
        },
        {
          "sigDif": "0",
          "sigDifKey": "2023_2022"
        }
      ]
    },
    "indicador-1-2": {
      "coordsX": [
        "2022"
      ],
      "dataPoints": [
        {
          "backgroundColor": "#5c5c5c",
          "borderColor": "#5c5c5c",
          "data": [
            "74"
          ],
          "label": "Puntaje promedio nacional del mismo GSE"
        },
        {
          "backgroundColor": "#043aa2",
          "borderColor": "#043aa2",
          "data": [
            "71"
          ],
          "label": "Puntaje promedio del establecimiento"
        }
      ],
      "dif": null,
      "format": 4,
      "mDif": "",
      "sigDif": null
    },
    "indicador-10": {
      "coordsX": [
        [
          "Números",
          "y Operaciones"
        ],
        [
          "Patrones y Álgebra"
        ],
        [
          "Geometría",
          "Medición"
        ],
        [
          "Datos y Probabilidades"
        ]
      ],
      "dataPoints": [
        [
          5
        ],
        [
          5
        ],
        [
          4
        ],
        [
          5
        ],
        [
          4
        ]
      ],
      "dif": null,
      "format": 1,
      "mDif": [
        "",
        "",
        "",
        "",
        ""
      ],
      "sigDif": null
    },
    "indicador-11-2": {
      "coordsX": [
        "2022"
      ],
      "dataPoints": [
        {
          "backgroundColor": "#5c5c5c",
          "borderColor": "#5c5c5c",
          "data": [
            ""
          ],
          "label": "Puntaje promedio nacional del mismo GSE"
        },
        {
          "backgroundColor": "#043aa2",
          "borderColor": "#043aa2",
          "data": [
            ""
          ],
          "label": "Puntaje promedio del establecimiento"
        }
      ],
      "dif": null,
      "format": 4,
      "mDif": "",
      "sigDif": null
    },
    "indicador-12-2": {
      "coordsX": [
        "2022"
      ],
      "dataPoints": [
        {
          "backgroundColor": "#5c5c5c",
          "borderColor": "#5c5c5c",
          "data": [
            ""
          ],
          "label": "Puntaje promedio nacional del mismo GSE"
        },
        {
          "backgroundColor": "#043aa2",
          "borderColor": "#043aa2",
          "data": [
            ""
          ],
          "label": "Puntaje promedio del establecimiento"
        }
      ],
      "dif": null,
      "format": 4,
      "mDif": "",
      "sigDif": null
    },
    "indicador-13-2": {
      "coordsX": [
        "2022"
      ],
      "dataPoints": [
        {
          "backgroundColor": "#5c5c5c",
          "borderColor": "#5c5c5c",
          "data": [
            ""
          ],
          "label": "Puntaje promedio nacional del mismo GSE"
        },
        {
          "backgroundColor": "#043aa2",
          "borderColor": "#043aa2",
          "data": [
            ""
          ],
          "label": "Puntaje promedio del establecimiento"
        }
      ],
      "dif": null,
      "format": 4,
      "mDif": "",
      "sigDif": null
    },
    "indicador-14-2": {
      "coordsX": [
        "2022"
      ],
      "dataPoints": [
        {
          "backgroundColor": "#5c5c5c",
          "borderColor": "#5c5c5c",
          "data": [
            ""
          ],
          "label": "Puntaje promedio nacional del mismo GSE"
        },
        {
          "backgroundColor": "#043aa2",
          "borderColor": "#043aa2",
          "data": [
            ""
          ],
          "label": "Puntaje promedio del establecimiento"
        }
      ],
      "dif": null,
      "format": 4,
      "mDif": "",
      "sigDif": null
    },
    "indicador-15-2": {
      "coordsX": [
        "2022"
      ],
      "dataPoints": [
        {
          "backgroundColor": "#5c5c5c",
          "borderColor": "#5c5c5c",
          "data": [
            ""
          ],
          "label": "Puntaje promedio nacional del mismo GSE"
        },
        {
          "backgroundColor": "#043aa2",
          "borderColor": "#043aa2",
          "data": [
            ""
          ],
          "label": "Puntaje promedio del establecimiento"
        }
      ],
      "dif": null,
      "format": 4,
      "mDif": "",
      "sigDif": null
    },
    "indicador-17": {
      "coordsX": [
        "Localizar",
        "Interpetrar y relacionar",
        "Reflexionar"
      ],
      "dataPoints": [
        [],
        [],
        []
      ],
      "dif": null,
      "format": 1,
      "mDif": [
        "",
        "",
        ""
      ],
      "sigDif": null
    },
    "indicador-18-2": {
      "coordsX": [
        "2022"
      ],
      "dataPoints": [
        {
          "backgroundColor": "#5c5c5c",
          "borderColor": "#5c5c5c",
          "data": [
            ""
          ],
          "label": "Puntaje promedio nacional del mismo GSE"
        },
        {
          "backgroundColor": "#043aa2",
          "borderColor": "#043aa2",
          "data": [
            ""
          ],
          "label": "Puntaje promedio del establecimiento"
        }
      ],
      "dif": null,
      "format": 4,
      "mDif": "",
      "sigDif": null
    },
    "indicador-2": {
      "coordsX": [
        "2016",
        "2017",
        "2018",
        "2022",
        "2023"
      ],
      "dataPoints": [
        "75",
        "65",
        "73",
        "81",
        "76"
      ],
      "dif": [
        {
          "dif": "-10",
          "difKey": "2017_2016"
        },
        {
          "dif": "8",
          "difKey": "2018_2017"
        },
        {
          "dif": "8",
          "difKey": "2022_2018"
        },
        {
          "dif": "-5",
          "difKey": "2023_2022"
        }
      ],
      "format": 1,
      "mDif": null,
      "sigDif": [
        {
          "sigDif": "-1",
          "sigDifKey": "2017_2016"
        },
        {
          "sigDif": "1",
          "sigDifKey": "2018_2017"
        },
        {
          "sigDif": "1",
          "sigDifKey": "2022_2018"
        },
        {
          "sigDif": "-1",
          "sigDifKey": "2023_2022"
        }
      ]
    },
    "indicador-2-2": {
      "coordsX": [
        "2022"
      ],
      "dataPoints": [
        {
          "backgroundColor": "#5c5c5c",
          "borderColor": "#5c5c5c",
          "data": [
            "75"
          ],
          "label": "Puntaje promedio nacional del mismo GSE"
        },
        {
          "backgroundColor": "#043aa2",
          "borderColor": "#043aa2",
          "data": [
            "76"
          ],
          "label": "Puntaje promedio del establecimiento"
        }
      ],
      "dif": null,
      "format": 4,
      "mDif": "",
      "sigDif": null
    },
    "indicador-20": {
      "coordsX": [
        [
          "Números"
        ],
        [
          "Álgebra y",
          "funciones"
        ],
        [
          "Geometría"
        ],
        [
          "Probabilidad y",
          "estadística"
        ]
      ],
      "dataPoints": [
        [],
        [],
        [],
        []
      ],
      "dif": null,
      "format": 1,
      "mDif": [
        "",
        "",
        "",
        ""
      ],
      "sigDif": null
    },
    "indicador-3": {
      "coordsX": [
        "2016",
        "2017",
        "2018",
        "2022",
        "2023"
      ],
      "dataPoints": [
        "78",
        "73",
        "75",
        "84",
        "80"
      ],
      "dif": [
        {
          "dif": "-5",
          "difKey": "2017_2016"
        },
        {
          "dif": "2",
          "difKey": "2018_2017"
        },
        {
          "dif": "9",
          "difKey": "2022_2018"
        },
        {
          "dif": "-4",
          "difKey": "2023_2022"
        }
      ],
      "format": 1,
      "mDif": null,
      "sigDif": [
        {
          "sigDif": "-1",
          "sigDifKey": "2017_2016"
        },
        {
          "sigDif": "0",
          "sigDifKey": "2018_2017"
        },
        {
          "sigDif": "1",
          "sigDifKey": "2022_2018"
        },
        {
          "sigDif": "-1",
          "sigDifKey": "2023_2022"
        }
      ]
    },
    "indicador-3-2": {
      "coordsX": [
        "2022"
      ],
      "dataPoints": [
        {
          "backgroundColor": "#5c5c5c",
          "borderColor": "#5c5c5c",
          "data": [
            "78"
          ],
          "label": "Puntaje promedio nacional del mismo GSE"
        },
        {
          "backgroundColor": "#043aa2",
          "borderColor": "#043aa2",
          "data": [
            "80"
          ],
          "label": "Puntaje promedio del establecimiento"
        }
      ],
      "dif": null,
      "format": 4,
      "mDif": "",
      "sigDif": null
    },
    "indicador-4-2": {
      "coordsX": [
        "2022"
      ],
      "dataPoints": [
        {
          "backgroundColor": "#5c5c5c",
          "borderColor": "#5c5c5c",
          "data": [
            "71"
          ],
          "label": "Puntaje promedio nacional del mismo GSE"
        },
        {
          "backgroundColor": "#043aa2",
          "borderColor": "#043aa2",
          "data": [
            "75"
          ],
          "label": "Puntaje promedio del establecimiento"
        }
      ],
      "dif": null,
      "format": 4,
      "mDif": "*",
      "sigDif": null
    },
    "indicador-5": {
      "coordsX": [
        "2016",
        "2017",
        "2018",
        "2022",
        "2023"
      ],
      "dataPoints": [
        "265",
        "253",
        "270",
        "278",
        "255"
      ],
      "dif": [
        {
          "dif": "-12",
          "difKey": "2017_2016"
        },
        {
          "dif": "17",
          "difKey": "2018_2017"
        },
        {
          "dif": "8",
          "difKey": "2022_2018"
        },
        {
          "dif": "-23",
          "difKey": "2023_2022"
        }
      ],
      "format": 1,
      "mDif": null,
      "sigDif": [
        {
          "sigDif": "0",
          "sigDifKey": "2017_2016"
        },
        {
          "sigDif": "1",
          "sigDifKey": "2018_2017"
        },
        {
          "sigDif": "0",
          "sigDifKey": "2022_2018"
        },
        {
          "sigDif": "-1",
          "sigDifKey": "2023_2022"
        }
      ]
    },
    "indicador-5-2": {
      "coordsX": [
        "2022"
      ],
      "dataPoints": [
        {
          "backgroundColor": "#5c5c5c",
          "borderColor": "#5c5c5c",
          "data": [
            "270"
          ],
          "label": "Puntaje promedio nacional del mismo GSE"
        },
        {
          "backgroundColor": "#043aa2",
          "borderColor": "#043aa2",
          "data": [
            "255"
          ],
          "label": "Puntaje promedio del establecimiento"
        }
      ],
      "dif": null,
      "format": 4,
      "mDif": "",
      "sigDif": null
    },
    "indicador-6": {
      "coordsX": [
        "2016",
        "2017",
        "2018",
        "2022",
        "2023"
      ],
      "dataPoints": [
        {
          "backgroundColor": "#87b4e2",
          "data": [
            "34.4",
            "38.7",
            "24.2",
            "22.6",
            "29.0"
          ],
          "label": "Nivel insuficiente"
        },
        {
          "backgroundColor": "#3dacea",
          "data": [
            "25.0",
            "25.8",
            "30.3",
            "16.1",
            "51.6"
          ],
          "label": "Nivel elemental"
        },
        {
          "backgroundColor": "#043aa2",
          "data": [
            "40.6",
            "35.5",
            "45.5",
            "61.3",
            "19.4"
          ],
          "label": "Nivel adecuado"
        }
      ],
      "dif": null,
      "format": 2,
      "mDif": [
        {
          "value": "",
          "year": "2016"
        },
        {
          "value": "",
          "year": "2017"
        },
        {
          "value": "",
          "year": "2018"
        },
        {
          "value": "",
          "year": "2022"
        },
        {
          "value": "",
          "year": "2023"
        },
        {
          "value": "",
          "year": "2016"
        },
        {
          "value": "",
          "year": "2017"
        },
        {
          "value": "",
          "year": "2018"
        },
        {
          "value": "",
          "year": "2022"
        },
        {
          "value": "",
          "year": "2023"
        },
        {
          "value": "",
          "year": "2016"
        },
        {
          "value": "",
          "year": "2017"
        },
        {
          "value": "",
          "year": "2018"
        },
        {
          "value": "",
          "year": "2022"
        },
        {
          "value": "",
          "year": "2023"
        }
      ],
      "sigDif": null
    },
    "indicador-7": {
      "coordsX": [
        "Localizar",
        "Interpretar y relacionar",
        "Reflexionar"
      ],
      "dataPoints": [
        [
          4
        ],
        [
          5
        ],
        [
          4
        ]
      ],
      "dif": null,
      "format": 1,
      "mDif": [
        "",
        "",
        ""
      ],
      "sigDif": null
    },
    "indicador-8": {
      "coordsX": [
        "2016",
        "2017",
        "2018",
        "2022",
        "2023"
      ],
      "dataPoints": [
        "260",
        "235",
        "251",
        "254",
        "249"
      ],
      "dif": [
        {
          "dif": "-25",
          "difKey": "2017_2016"
        },
        {
          "dif": "16",
          "difKey": "2018_2017"
        },
        {
          "dif": "3",
          "difKey": "2022_2018"
        },
        {
          "dif": "-5",
          "difKey": "2023_2022"
        }
      ],
      "format": 1,
      "mDif": null,
      "sigDif": [
        {
          "sigDif": "-1",
          "sigDifKey": "2017_2016"
        },
        {
          "sigDif": "1",
          "sigDifKey": "2018_2017"
        },
        {
          "sigDif": "0",
          "sigDifKey": "2022_2018"
        },
        {
          "sigDif": "0",
          "sigDifKey": "2023_2022"
        }
      ]
    },
    "indicador-8-2": {
      "coordsX": [
        "2022"
      ],
      "dataPoints": [
        {
          "backgroundColor": "#5c5c5c",
          "borderColor": "#5c5c5c",
          "data": [
            "256"
          ],
          "label": "Puntaje promedio nacional del mismo GSE"
        },
        {
          "backgroundColor": "#043aa2",
          "borderColor": "#043aa2",
          "data": [
            "249"
          ],
          "label": "Puntaje promedio del establecimiento"
        }
      ],
      "dif": null,
      "format": 4,
      "mDif": "",
      "sigDif": null
    },
    "indicador-9": {
      "coordsX": [
        "2016",
        "2017",
        "2018",
        "2022",
        "2023"
      ],
      "dataPoints": [
        {
          "backgroundColor": "#87b4e2",
          "data": [
            "43.8",
            "57.6",
            "45.5",
            "38.7",
            "41.9"
          ],
          "label": "Nivel insuficiente"
        },
        {
          "backgroundColor": "#3dacea",
          "data": [
            "34.4",
            "30.3",
            "39.4",
            "38.7",
            "48.4"
          ],
          "label": "Nivel elemental"
        },
        {
          "backgroundColor": "#043aa2",
          "data": [
            "21.9",
            "12.1",
            "15.2",
            "22.6",
            "9.7"
          ],
          "label": "Nivel adecuado"
        }
      ],
      "dif": null,
      "format": 2,
      "mDif": [
        {
          "value": "",
          "year": "2016"
        },
        {
          "value": "",
          "year": "2017"
        },
        {
          "value": "",
          "year": "2018"
        },
        {
          "value": "",
          "year": "2022"
        },
        {
          "value": "",
          "year": "2023"
        },
        {
          "value": "",
          "year": "2016"
        },
        {
          "value": "",
          "year": "2017"
        },
        {
          "value": "",
          "year": "2018"
        },
        {
          "value": "",
          "year": "2022"
        },
        {
          "value": "",
          "year": "2023"
        },
        {
          "value": "",
          "year": "2016"
        },
        {
          "value": "",
          "year": "2017"
        },
        {
          "value": "",
          "year": "2018"
        },
        {
          "value": "",
          "year": "2022"
        },
        {
          "value": "",
          "year": "2023"
        }
      ],
      "sigDif": null
    }
  },
  "dimensiones": {
    "dimension-21": {
      "coordsX": [
        "2016",
        "2017",
        "2018",
        "2022",
        "2023"
      ],
      "dataPoints": [
        "71",
        "65",
        "71",
        "72",
        "67"
      ],
      "dif": [
        {
          "dif": "-6",
          "difKey": "2017_2016"
        },
        {
          "dif": "6",
          "difKey": "2018_2017"
        },
        {
          "dif": "1",
          "difKey": "2022_2018"
        },
        {
          "dif": "-5",
          "difKey": "2023_2022"
        }
      ],
      "format": 1,
      "mDif": null,
      "sigDif": [
        {
          "sigDif": "-1",
          "sigDifKey": "2017_2016"
        },
        {
          "sigDif": "1",
          "sigDifKey": "2018_2017"
        },
        {
          "sigDif": "0",
          "sigDifKey": "2022_2018"
        },
        {
          "sigDif": "-1",
          "sigDifKey": "2023_2022"
        }
      ]
    },
    "dimension-22": {
      "coordsX": [
        "2016",
        "2017",
        "2018",
        "2022",
        "2023"
      ],
      "dataPoints": [
        "74",
        "73",
        "73",
        "76",
        "75"
      ],
      "dif": [
        {
          "dif": "-1",
          "difKey": "2017_2016"
        },
        {
          "dif": "0",
          "difKey": "2018_2017"
        },
        {
          "dif": "3",
          "difKey": "2022_2018"
        },
        {
          "dif": "-1",
          "difKey": "2023_2022"
        }
      ],
      "format": 1,
      "mDif": null,
      "sigDif": [
        {
          "sigDif": "0",
          "sigDifKey": "2017_2016"
        },
        {
          "sigDif": "0",
          "sigDifKey": "2018_2017"
        },
        {
          "sigDif": "0",
          "sigDifKey": "2022_2018"
        },
        {
          "sigDif": "0",
          "sigDifKey": "2023_2022"
        }
      ]
    },
    "dimension-23": {
      "coordsX": [
        "2016",
        "2017",
        "2018",
        "2022",
        "2023"
      ],
      "dataPoints": [
        "71",
        "61",
        "66",
        "73",
        "71"
      ],
      "dif": [
        {
          "dif": "-10",
          "difKey": "2017_2016"
        },
        {
          "dif": "5",
          "difKey": "2018_2017"
        },
        {
          "dif": "7",
          "difKey": "2022_2018"
        },
        {
          "dif": "-2",
          "difKey": "2023_2022"
        }
      ],
      "format": 1,
      "mDif": null,
      "sigDif": [
        {
          "sigDif": "-1",
          "sigDifKey": "2017_2016"
        },
        {
          "sigDif": "1",
          "sigDifKey": "2018_2017"
        },
        {
          "sigDif": "1",
          "sigDifKey": "2022_2018"
        },
        {
          "sigDif": "0",
          "sigDifKey": "2023_2022"
        }
      ]
    },
    "dimension-24": {
      "coordsX": [
        "2016",
        "2017",
        "2018",
        "2022",
        "2023"
      ],
      "dataPoints": [
        "78",
        "70",
        "78",
        "86",
        "81"
      ],
      "dif": [
        {
          "dif": "-8",
          "difKey": "2017_2016"
        },
        {
          "dif": "8",
          "difKey": "2018_2017"
        },
        {
          "dif": "8",
          "difKey": "2022_2018"
        },
        {
          "dif": "-5",
          "difKey": "2023_2022"
        }
      ],
      "format": 1,
      "mDif": null,
      "sigDif": [
        {
          "sigDif": "-1",
          "sigDifKey": "2017_2016"
        },
        {
          "sigDif": "1",
          "sigDifKey": "2018_2017"
        },
        {
          "sigDif": "1",
          "sigDifKey": "2022_2018"
        },
        {
          "sigDif": "-1",
          "sigDifKey": "2023_2022"
        }
      ]
    },
    "dimension-25": {
      "coordsX": [
        "2016",
        "2017",
        "2018",
        "2022",
        "2023"
      ],
      "dataPoints": [
        "76",
        "64",
        "74",
        "84",
        "76"
      ],
      "dif": [
        {
          "dif": "-12",
          "difKey": "2017_2016"
        },
        {
          "dif": "10",
          "difKey": "2018_2017"
        },
        {
          "dif": "10",
          "difKey": "2022_2018"
        },
        {
          "dif": "-8",
          "difKey": "2023_2022"
        }
      ],
      "format": 1,
      "mDif": null,
      "sigDif": [
        {
          "sigDif": "-1",
          "sigDifKey": "2017_2016"
        },
        {
          "sigDif": "1",
          "sigDifKey": "2018_2017"
        },
        {
          "sigDif": "1",
          "sigDifKey": "2022_2018"
        },
        {
          "sigDif": "-1",
          "sigDifKey": "2023_2022"
        }
      ]
    },
    "dimension-26": {
      "coordsX": [
        "2016",
        "2017",
        "2018",
        "2022",
        "2023"
      ],
      "dataPoints": [
        "77",
        "73",
        "75",
        "81",
        "80"
      ],
      "dif": [
        {
          "dif": "-4",
          "difKey": "2017_2016"
        },
        {
          "dif": "2",
          "difKey": "2018_2017"
        },
        {
          "dif": "6",
          "difKey": "2022_2018"
        },
        {
          "dif": "-1",
          "difKey": "2023_2022"
        }
      ],
      "format": 1,
      "mDif": null,
      "sigDif": [
        {
          "sigDif": "0",
          "sigDifKey": "2017_2016"
        },
        {
          "sigDif": "0",
          "sigDifKey": "2018_2017"
        },
        {
          "sigDif": "1",
          "sigDifKey": "2022_2018"
        },
        {
          "sigDif": "0",
          "sigDifKey": "2023_2022"
        }
      ]
    },
    "dimension-27": {
      "coordsX": [
        "2016",
        "2017",
        "2018",
        "2022",
        "2023"
      ],
      "dataPoints": [
        "79",
        "71",
        "77",
        "84",
        "76"
      ],
      "dif": [
        {
          "dif": "-8",
          "difKey": "2017_2016"
        },
        {
          "dif": "6",
          "difKey": "2018_2017"
        },
        {
          "dif": "7",
          "difKey": "2022_2018"
        },
        {
          "dif": "-8",
          "difKey": "2023_2022"
        }
      ],
      "format": 1,
      "mDif": null,
      "sigDif": [
        {
          "sigDif": "-1",
          "sigDifKey": "2017_2016"
        },
        {
          "sigDif": "1",
          "sigDifKey": "2018_2017"
        },
        {
          "sigDif": "1",
          "sigDifKey": "2022_2018"
        },
        {
          "sigDif": "-1",
          "sigDifKey": "2023_2022"
        }
      ]
    },
    "dimension-28": {
      "coordsX": [
        "2016",
        "2017",
        "2018",
        "2022",
        "2023"
      ],
      "dataPoints": [
        "77",
        "75",
        "72",
        "86",
        "85"
      ],
      "dif": [
        {
          "dif": "-2",
          "difKey": "2017_2016"
        },
        {
          "dif": "-3",
          "difKey": "2018_2017"
        },
        {
          "dif": "14",
          "difKey": "2022_2018"
        },
        {
          "dif": "-1",
          "difKey": "2023_2022"
        }
      ],
      "format": 1,
      "mDif": null,
      "sigDif": [
        {
          "sigDif": "0",
          "sigDifKey": "2017_2016"
        },
        {
          "sigDif": "0",
          "sigDifKey": "2018_2017"
        },
        {
          "sigDif": "1",
          "sigDifKey": "2022_2018"
        },
        {
          "sigDif": "0",
          "sigDifKey": "2023_2022"
        }
      ]
    },
    "dimension-29": {
      "coordsX": [
        "2016",
        "2017",
        "2018",
        "2022",
        "2023"
      ],
      "dataPoints": [
        "65",
        "74",
        "70",
        "78",
        "75"
      ],
      "dif": [
        {
          "dif": "9",
          "difKey": "2017_2016"
        },
        {
          "dif": "-4",
          "difKey": "2018_2017"
        },
        {
          "dif": "8",
          "difKey": "2022_2018"
        },
        {
          "dif": "-3",
          "difKey": "2023_2022"
        }
      ],
      "format": 1,
      "mDif": null,
      "sigDif": [
        {
          "sigDif": "1",
          "sigDifKey": "2017_2016"
        },
        {
          "sigDif": "0",
          "sigDifKey": "2018_2017"
        },
        {
          "sigDif": "1",
          "sigDifKey": "2022_2018"
        },
        {
          "sigDif": "0",
          "sigDifKey": "2023_2022"
        }
      ]
    }
  }
}